CLASSIFIERS
LICENSE
MANIFEST.in
README.rst
requirements.pip
setup.cfg
setup.py
src/clickatell/__init__.py
src/clickatell/api.py
src/clickatell/client.py
src/clickatell/constants.py
src/clickatell/errors.py
src/clickatell/http.py
src/clickatell/response.py
src/clickatell/url.py
src/clickatell/utils.py
src/clickatell/validators.py
src/clickatell/tests/__init__.py
src/clickatell/tests/mock.py
src/python_clickatell.egg-info/PKG-INFO
src/python_clickatell.egg-info/SOURCES.txt
src/python_clickatell.egg-info/dependency_links.txt
src/python_clickatell.egg-info/requires.txt
src/python_clickatell.egg-info/top_level.txt