Metadata-Version: 1.0
Name: python-clickatell
Version: 0.1.3
Summary: Clickatell HTTP library
Home-page: http://github.com/smn/bellville
Author: Simon de Haan
Author-email: simon@praekeltfoundation.org
License: BSD
Platform: UNKNOWN
Classifier: Development Status :: 5 - Production/Stable
Classifier: Intended Audience :: Developers
Classifier: License :: OSI Approved :: BSD License
Classifier: Operating System :: OS Independent
Classifier: Programming Language :: Python
Classifier: Topic :: Software Development :: Libraries :: Python Modules
